MANIFEST.in
README.rst
setup.py
palette/__init__.py
palette.egg-info/PKG-INFO
palette.egg-info/SOURCES.txt
palette.egg-info/dependency_links.txt
palette.egg-info/not-zip-safe
palette.egg-info/top_level.txt
palette/tests/__init__.py
palette/tests/test_palette.py