Metadata-Version: 1.0
Name: palette
Version: 0.2
Summary: Easy color manipulation for Python.
Home-page: http://github.com/deactivated/palette
Author: Mike Spindel
Author-email: mike@spindel.is
License: MIT
Keywords: color colorspace rgb hls hsl
Platform: UNKNOWN
Classifier: Development Status :: 4 - Beta
Classifier: License :: OSI Approved :: MIT License
Classifier: Intended Audience :: Developers
Classifier: Natural Language :: English
Classifier: Programming Language :: Python
